wandarr/__init__.py
wandarr/__main__.py
wandarr/agent.py
wandarr/agenthost.py
wandarr/base.py
wandarr/cluster.py
wandarr/config.py
wandarr/ffmpeg.py
wandarr/localhost.py
wandarr/media.py
wandarr/mountedhost.py
wandarr/streaminghost.py
wandarr/template.py
wandarr/transcode.py
wandarr/utils.py
wandarr-1.1.2.dist-info/METADATA
wandarr-1.1.2.dist-info/WHEEL
wandarr-1.1.2.dist-info/entry_points.txt
wandarr-1.1.2.dist-info/licenses/LICENSE
wandarr-1.1.2.dist-info/RECORD
