Metadata-Version: 2.4
Name: wandarr
Version: 1.1.2
Summary: A ffmpeg transcoding workflow engine with clustered host support
Project-URL: Homepage, https://github.com/mlsmithjr/wandarr
Author-email: Marshall L Smith Jr <marshallsmithjr@gmail.com>
License-File: LICENSE
Keywords: cuda,encode,ffmpeg,qsv,transcode
Classifier: Environment :: Console
Classifier: Intended Audience :: End Users/Desktop
Classifier: License :: OSI Approved :: GNU General Public License v3 (GPLv3)
Classifier: Natural Language :: English
Classifier: Operating System :: MacOS :: MacOS X
Classifier: Operating System :: Microsoft :: Windows
Classifier: Operating System :: POSIX :: Linux
Classifier: Programming Language :: Python :: 3
Classifier: Topic :: Multimedia :: Video :: Conversion
Requires-Python: >=3.10
Requires-Dist: pyyaml>=6.0
Requires-Dist: rich>=13.5.3
